{
  "scriptId": "337",
  "url": "file:///Users/nv/repos/0x4007/os.ubq.fi/src/server.ts",
  "functions": [
    {
      "functionName": "",
      "ranges": [
        {
          "startOffset": 0,
          "endOffset": 2805,
          "count": 1
        },
        {
          "startOffset": 2536,
          "endOffset": 2804,
          "count": 0
        }
      ],
      "isBlockCoverage": true
    },
    {
      "functionName": "handler",
      "ranges": [
        {
          "startOffset": 178,
          "endOffset": 2163,
          "count": 4
        },
        {
          "startOffset": 337,
          "endOffset": 1865,
          "count": 3
        },
        {
          "startOffset": 376,
          "endOffset": 399,
          "count": 1
        },
        {
          "startOffset": 401,
          "endOffset": 539,
          "count": 1
        },
        {
          "startOffset": 539,
          "endOffset": 575,
          "count": 2
        },
        {
          "startOffset": 575,
          "endOffset": 598,
          "count": 1
        },
        {
          "startOffset": 600,
          "endOffset": 802,
          "count": 1
        },
        {
          "startOffset": 804,
          "endOffset": 1834,
          "count": 1
        },
        {
          "startOffset": 857,
          "endOffset": 862,
          "count": 0
        },
        {
          "startOffset": 996,
          "endOffset": 1769,
          "count": 0
        },
        {
          "startOffset": 1834,
          "endOffset": 1865,
          "count": 0
        },
        {
          "startOffset": 1865,
          "endOffset": 2025,
          "count": 1
        },
        {
          "startOffset": 2025,
          "endOffset": 2161,
          "count": 0
        }
      ],
      "isBlockCoverage": true
    },
    {
      "functionName": "",
      "ranges": [
        {
          "startOffset": 976,
          "endOffset": 984,
          "count": 0
        }
      ],
      "isBlockCoverage": false
    },
    {
      "functionName": "",
      "ranges": [
        {
          "startOffset": 1075,
          "endOffset": 1083,
          "count": 0
        }
      ],
      "isBlockCoverage": false
    },
    {
      "functionName": "",
      "ranges": [
        {
          "startOffset": 1749,
          "endOffset": 1757,
          "count": 0
        }
      ],
      "isBlockCoverage": false
    },
    {
      "functionName": "json",
      "ranges": [
        {
          "startOffset": 2164,
          "endOffset": 2430,
          "count": 3
        }
      ],
      "isBlockCoverage": true
    },
    {
      "functionName": "notFound",
      "ranges": [
        {
          "startOffset": 2431,
          "endOffset": 2513,
          "count": 0
        }
      ],
      "isBlockCoverage": false
    },
    {
      "functionName": "onListen",
      "ranges": [
        {
          "startOffset": 2583,
          "endOffset": 2787,
          "count": 0
        }
      ],
      "isBlockCoverage": false
    }
  ]
}